README.txt
setup.cfg
setup.py
pjson/__init__.py
pjson/__main__.py
pjson/core.py
pjson.egg-info/PKG-INFO
pjson.egg-info/SOURCES.txt
pjson.egg-info/dependency_links.txt
pjson.egg-info/entry_points.txt
pjson.egg-info/requires.txt
pjson.egg-info/top_level.txt