Metadata-Version: 1.1
Name: pjson
Version: 1.1
Summary: Command-line tool to validate and pretty-print JSON and XML.
Home-page: http://igorgue.com/pjson
Author: Igor Guerrero
Author-email: igfgt1@gmail.com
License: MIT
Keywords: json xml
Platform: UNKNOWN
Classifier: Development Status :: 2 - Pre-Alpha
Classifier: Intended Audience :: Developers
Classifier: Natural Language :: English
Classifier: Operating System :: POSIX
Classifier: Programming Language :: Python
Classifier: License :: OSI Approved :: MIT License
